castorapi/__init__.py
castorapi/castorapi.py
castorapi-0.3.dist-info/LICENSE
castorapi-0.3.dist-info/METADATA
castorapi-0.3.dist-info/WHEEL
castorapi-0.3.dist-info/top_level.txt
castorapi-0.3.dist-info/RECORD
