Metadata-Version: 2.1
Name: castorapi
Version: 0.3
Summary: Python API wrapper for Castor EDC to fetch data from you clinical study.
Home-page: https://github.com/wouterpotters/castorapi
Download-URL: https://github.com/wouterpotters/castorapi/archive/master.zip
Author: Wouter V. Potters
Author-email: w.v.potters@amsterdamumc.nl
License: MIT
Keywords: Castor EDC,API,Castor,Clinical study,database,data science
Classifier: Development Status :: 3 - Alpha
Classifier: Intended Audience :: Developers
Classifier: Topic :: Software Development :: Build Tools
Classifier: License :: OSI Approved :: MIT License
Classifier: Programming Language :: Python :: 3
License-File: LICENSE
Requires-Dist: pandas >=1.0
Requires-Dist: requests >=2.23
Requires-Dist: progressbar2 >=3.5
